azure/ai/language/conversations/authoring/__init__.py
azure/ai/language/conversations/authoring/_client.py
azure/ai/language/conversations/authoring/_configuration.py
azure/ai/language/conversations/authoring/_patch.py
azure/ai/language/conversations/authoring/_validation.py
azure/ai/language/conversations/authoring/_version.py
azure/ai/language/conversations/authoring/py.typed
azure/ai/language/conversations/authoring/_utils/__init__.py
azure/ai/language/conversations/authoring/_utils/model_base.py
azure/ai/language/conversations/authoring/_utils/serialization.py
azure/ai/language/conversations/authoring/_utils/utils.py
azure/ai/language/conversations/authoring/aio/__init__.py
azure/ai/language/conversations/authoring/aio/_client.py
azure/ai/language/conversations/authoring/aio/_configuration.py
azure/ai/language/conversations/authoring/aio/_patch.py
azure/ai/language/conversations/authoring/aio/operations/__init__.py
azure/ai/language/conversations/authoring/aio/operations/_deployment_op_patch.py
azure/ai/language/conversations/authoring/aio/operations/_operations.py
azure/ai/language/conversations/authoring/aio/operations/_patch.py
azure/ai/language/conversations/authoring/aio/operations/_project_op_patch.py
azure/ai/language/conversations/authoring/models/__init__.py
azure/ai/language/conversations/authoring/models/_enums.py
azure/ai/language/conversations/authoring/models/_models.py
azure/ai/language/conversations/authoring/models/_patch.py
azure/ai/language/conversations/authoring/operations/__init__.py
azure/ai/language/conversations/authoring/operations/_deployment_op_patch.py
azure/ai/language/conversations/authoring/operations/_operations.py
azure/ai/language/conversations/authoring/operations/_patch.py
azure/ai/language/conversations/authoring/operations/_project_op_patch.py
azure_ai_language_conversations_authoring-1.0.0b3.dist-info/licenses/LICENSE
azure_ai_language_conversations_authoring-1.0.0b3.dist-info/METADATA
azure_ai_language_conversations_authoring-1.0.0b3.dist-info/WHEEL
azure_ai_language_conversations_authoring-1.0.0b3.dist-info/top_level.txt
azure_ai_language_conversations_authoring-1.0.0b3.dist-info/RECORD
